{
  "group_name": "Time Words",
  "words": [
    {
      "japanese": "今日",
      "romaji": "kyou",
      "english": "today",
      "parts": null
    },
    {
      "japanese": "明日",
      "romaji": "ashita",
      "english": "tomorrow",
      "parts": null
    },
    {
      "japanese": "昨日",
      "romaji": "kinou",
      "english": "yesterday",
      "parts": null
    },
    {
      "japanese": "朝",
      "romaji": "asa",
      "english": "morning",
      "parts": null
    },
    {
      "japanese": "昼",
      "romaji": "hiru",
      "english": "noon/daytime",
      "parts": null
    },
    {
      "japanese": "夜",
      "romaji": "yoru",
      "english": "night",
      "parts": null
    }
  ]
} 